<?xml version="1.0" encoding="utf-8"?>
<board>
    <name>prueba</name>
    <columns>5</columns>
    <rows>6</rows>
    <ways>4</ways>
    <A>255</A>
    <R>0</R>
    <G>128</G>
    <B>0</B>
    <maxTime>300</maxTime>
    <visualHelp>False</visualHelp>
    <helpTime>10</helpTime>
    <simpleResults>True</simpleResults>
    <detailedResults>False</detailedResults>
    <goodInterval>100</goodInterval>
    <regularInterval>90</regularInterval>
    <badInterval>50</badInterval>
    <goodMsg>GREAT!</goodMsg>
    <regularMsg>GREAT!</regularMsg>
    <badMsg>GREAT!</badMsg>
    <allowTutorial>True</allowTutorial>
    <allowAuditoryTutorial>True</allowAuditoryTutorial>
    <sound>True</sound>
    <hapticHelp>True</hapticHelp>
    <eyepatch>0</eyepatch>
    <screenshot>True</screenshot>
    <description>Prueba de ajustes</description>
    <goodRetry>False</goodRetry>
    <regularRetry>False</regularRetry>
    <badRetry>True</badRetry>
    <bell>dog</bell>
    <cells>
        <info>sphere</info>
        <info>dog</info>
        <info>jraffe</info>
        <info>candy</info>
        <info>candy</info>
        <info>ball</info>
        <info>teddy</info>
        <info>dog</info>
        <info>sphere</info>
        <info>flower</info>
        <info>dog</info>
        <info>sphere</info>
        <info>teddy</info>
        <info>ball</info>
        <info>dog</info>
        <info>tree</info>
        <info>sphere</info>
        <info>square</info>
        <info>flower</info>
        <info>dog</info>
        <info>jraffe</info>
        <info>tree</info>
        <info>sphere</info>
        <info>dog</info>
        <info>teddy</info>
        <info>sphere</info>
        <info>candy</info>
        <info>jraffe</info>
        <info>teddy</info>
        <info>dog</info>
        <info>dog</info>
        <info>teddy</info>
        <info>triangle</info>
        <info>teddy</info>
        <info>dog</info>
        <info>flower</info>
        <info>flower</info>
        <info>dog</info>
        <info>dog</info>
        <info>ball</info>
        <info>dog</info>
        <info>tree</info>
        <info>candy</info>
        <info>tree</info>
        <info>sphere</info>
        <info>triangle</info>
        <info>dog</info>
        <info>teddy</info>
        <info>dog</info>
        <info>dog</info>
        <info>tree</info>
        <info>teddy</info>
        <info>flower</info>
        <info>bird</info>
        <info>sphere</info>
        <info>square</info>
        <info>teddy</info>
        <info>bird</info>
        <info>ball</info>
        <info>flower</info>
        <info>candy</info>
        <info>teddy</info>
        <info>dog</info>
        <info>dog</info>
        <info>dog</info>
        <info>bird</info>
        <info>tree</info>
        <info>candy</info>
        <info>ball</info>
        <info>triangle</info>
        <info>dog</info>
        <info>dog</info>
        <info>jraffe</info>
        <info>dog</info>
        <info>teddy</info>
        <info>dog</info>
        <info>ball</info>
        <info>candy</info>
        <info>bird</info>
        <info>tree</info>
        <info>dog</info>
        <info>flower</info>
        <info>sphere</info>
        <info>triangle</info>
        <info>dog</info>
        <info>dog</info>
        <info>teddy</info>
        <info>dog</info>
        <info>candy</info>
        <info>ball</info>
        <info>dog</info>
        <info>square</info>
        <info>tree</info>
        <info>triangle</info>
        <info>dog</info>
        <info>dog</info>
        <info>tree</info>
        <info>jraffe</info>
        <info>dog</info>
        <info>dog</info>
        <info>jraffe</info>
        <info>dog</info>
        <info>triangle</info>
        <info>dog</info>
        <info>jraffe</info>
        <info>dog</info>
        <info>dog</info>
        <info>bird</info>
        <info>flower</info>
        <info>dog</info>
        <info>triangle</info>
        <info>dog</info>
        <info>candy</info>
        <info>triangle</info>
        <info>bird</info>
        <info>candy</info>
        <info>dog</info>
        <info>square</info>
        <info>dog</info>
        <info>dog</info>
    </cells>
</board>
